stix_shifter_modules/elastic/__init__.py
stix_shifter_modules/elastic/entry_point.py
stix_shifter_modules/elastic/stix_translation/__init__.py
stix_shifter_modules/elastic/stix_translation/car_query_translator.py
stix_shifter_modules/elastic/stix_translation/cim_query_translator.py
stix_shifter_modules/elastic/stix_translation/query_constructor.py
stix_shifter_modules/elastic/stix_translation/results_translator.py
stix_shifter_modules_elastic-3.1.8.dist-info/LICENSE.md
stix_shifter_modules_elastic-3.1.8.dist-info/METADATA
stix_shifter_modules_elastic-3.1.8.dist-info/NOTICE
stix_shifter_modules_elastic-3.1.8.dist-info/WHEEL
stix_shifter_modules_elastic-3.1.8.dist-info/top_level.txt
stix_shifter_modules_elastic-3.1.8.dist-info/RECORD
